__init__.py
scratch.py
eccs/__init__.py
eccs/ate.py
eccs/eccs.py
eccs/edge_state_matrix.py
eccs/edges.py
eccs/graph_renderer.py
eccs/heuristic_search.py
eccs/map_adj_set_to_graph.py
eccs/printer.py
evaluation/__init__.py
evaluation/heuristic_test_runner.py
evaluation/iterative_runner.py
evaluation/plotter.py
evaluation/simple_runner.py
evaluation/user.py
generators/__init__.py
generators/random_dag_generator.py
generators/random_dataset_generator.py
eccs-0.1.4.dist-info/LICENSE
eccs-0.1.4.dist-info/METADATA
eccs-0.1.4.dist-info/WHEEL
eccs-0.1.4.dist-info/top_level.txt
eccs-0.1.4.dist-info/RECORD
