Metadata-Version: 2.1
Name: eccs
Version: 0.1.4
Summary: Code for the 'Exposing Critical Causal Structures' project.
Author-email: Markos Markakis <markakis@mit.edu>, Sylvia Ziyu Zhang <sylziyuz@mit.edu>
Project-URL: Code, https://github.com/mmarkakis/eccs
Project-URL: Docs, https://mmarkakis.github.io/eccs/
Classifier: Programming Language :: Python :: 3
Classifier: License :: OSI Approved :: MIT License
Classifier: Operating System :: OS Independent
Requires-Python: <3.12,>=3.8
License-File: LICENSE
Requires-Dist: dihash
Requires-Dist: dowhy >=0.11.1
Requires-Dist: ipykernel >=6.29.2
Requires-Dist: ipython >=8.18.0
Requires-Dist: networkx >=3.2.1
Requires-Dist: numpy >=1.26.1
Requires-Dist: pandas >=2.2.0
Requires-Dist: pydot >=2.0.0
Requires-Dist: scikit-learn >=1.3.2
Requires-Dist: tqdm >=4.66.2
Requires-Dist: numpy
Provides-Extra: docs
Requires-Dist: markdown ; extra == 'docs'
Requires-Dist: markdown-include ; extra == 'docs'
Requires-Dist: mdx-include ; extra == 'docs'
Requires-Dist: mkdocs-gen-files ; extra == 'docs'
Requires-Dist: mkdocs-jupyter ; extra == 'docs'
Requires-Dist: mkdocs-literate-nav ; extra == 'docs'
Requires-Dist: mkdocs-material ; extra == 'docs'
Requires-Dist: mkdocs-section-index ; extra == 'docs'
Requires-Dist: mkdocstrings ; extra == 'docs'
Requires-Dist: mkdocstrings-python ; extra == 'docs'
Requires-Dist: Pygments ; extra == 'docs'
Requires-Dist: pymdown-extensions ; extra == 'docs'
